showtime/__init__.py
showtime/show_type.py
showtime/show_type_pb2.py
showtime/showspider_factory.py
showtime/utils.py
showtime/webspider.py
show_time-0.0.5.dist-info/LICENSE
show_time-0.0.5.dist-info/METADATA
show_time-0.0.5.dist-info/WHEEL
show_time-0.0.5.dist-info/top_level.txt
show_time-0.0.5.dist-info/RECORD
