Metadata-Version: 2.1
Name: show-time
Version: 0.0.5
Summary: A tool based on network spider technology to crawl information for numerous shows such as dramas and concerts.
Home-page: https://github.com/barrierye/showtime
Author: barriery
Author-email: barriery@qq.com
Maintainer: barriery
Maintainer-email: barriery@qq.com
License: MIT
Keywords: show spider
Platform: UNKNOWN
Classifier: Programming Language :: Python :: 3
Classifier: License :: OSI Approved :: MIT License
Requires-Python: >=3.5
Requires-Dist: beautifulsoup4 (==4.8.1)
Requires-Dist: lxml (==4.4.1)
Requires-Dist: aiohttp (==3.6.2)
Requires-Dist: requests (==2.22.0)
Requires-Dist: protobuf (==3.10.0)
